odoo/addons/account_invoice_report_product_sticker/README.rst
odoo/addons/account_invoice_report_product_sticker/__init__.py
odoo/addons/account_invoice_report_product_sticker/__manifest__.py
odoo/addons/account_invoice_report_product_sticker/i18n/account_invoice_report_product_sticker.pot
odoo/addons/account_invoice_report_product_sticker/i18n/es.po
odoo/addons/account_invoice_report_product_sticker/i18n/it.po
odoo/addons/account_invoice_report_product_sticker/models/__init__.py
odoo/addons/account_invoice_report_product_sticker/models/account_move.py
odoo/addons/account_invoice_report_product_sticker/models/res_config_settings.py
odoo/addons/account_invoice_report_product_sticker/readme/CONTRIBUTORS.md
odoo/addons/account_invoice_report_product_sticker/readme/DESCRIPTION.md
odoo/addons/account_invoice_report_product_sticker/readme/INSTALL.md
odoo/addons/account_invoice_report_product_sticker/readme/USAGE.md
odoo/addons/account_invoice_report_product_sticker/static/description/icon.png
odoo/addons/account_invoice_report_product_sticker/static/description/index.html
odoo/addons/account_invoice_report_product_sticker/tests/__init__.py
odoo/addons/account_invoice_report_product_sticker/tests/common.py
odoo/addons/account_invoice_report_product_sticker/tests/test_account_move.py
odoo/addons/account_invoice_report_product_sticker/views/account_move_view.xml
odoo/addons/account_invoice_report_product_sticker/views/report_invoice.xml
odoo/addons/account_invoice_report_product_sticker/views/res_config_settings_view.xml
odoo_addon_account_invoice_report_product_sticker-18.0.1.0.1.dist-info/METADATA
odoo_addon_account_invoice_report_product_sticker-18.0.1.0.1.dist-info/WHEEL
odoo_addon_account_invoice_report_product_sticker-18.0.1.0.1.dist-info/top_level.txt
odoo_addon_account_invoice_report_product_sticker-18.0.1.0.1.dist-info/RECORD
